ebmdatalab/__init__.py
ebmdatalab/bq.py
ebmdatalab/charts.py
ebmdatalab/maps.py
ebmdatalab/stats.py
ebmdatalab/data/ccg_for_map.csv
ebmdatalab/data/ccgs_2018.json
ebmdatalab/data/ccgs_2019.json
ebmdatalab/data/ccgs_2020.json
ebmdatalab/data/ccgs_cartogram_2019.json
ebmdatalab/data/ccgs_cartogram_2020.json
ebmdatalab/tests/__init__.py
ebmdatalab/tests/test_bq.py
ebmdatalab/tests/test_charts.py
ebmdatalab/tests/test_maps.py
ebmdatalab/tests/test_stats.py
ebmdatalab-0.0.31.dist-info/LICENSE
ebmdatalab-0.0.31.dist-info/WHEEL
ebmdatalab-0.0.31.dist-info/METADATA
ebmdatalab-0.0.31.dist-info/RECORD
