Metadata-Version: 2.1
Name: ebmdatalab
Version: 0.0.31
Summary: Package for ebmdatalab jupyter notebook stuff
Home-page: https://github.com/ebmdatalab/datalab-pandas
Author: EBM DataLab
Author-email: tech@ebmdatalab.net
Classifier: License :: OSI Approved :: MIT License
Requires-Dist: statsmodels
Requires-Dist: seaborn
Requires-Dist: pandas >= 0.24
Requires-Dist: pandas-gbq >= 0.8.0
Requires-Dist: geopandas
Requires-Dist: descartes
Requires-Dist: pytest >=2.7.3 ; extra == "test"
Provides-Extra: test
